create_py_app/__init__.py
create_py_app/create_files.py
create_py_app/file_contents.yml
create_py_app/main.py
create_py_app-0.1.9.dist-info/LICENSE
create_py_app-0.1.9.dist-info/METADATA
create_py_app-0.1.9.dist-info/WHEEL
create_py_app-0.1.9.dist-info/entry_points.txt
create_py_app-0.1.9.dist-info/top_level.txt
create_py_app-0.1.9.dist-info/RECORD
