Metadata-Version: 2.1
Name: create-py-app
Version: 0.1.9
Summary: A tool for creating a simple python framework
Home-page: https://github.com/hyoshida123/create-py-app
Author: Hideaki Yoshida
Author-email: 
Classifier: Programming Language :: Python :: 3
Classifier: License :: OSI Approved :: MIT License
Classifier: Operating System :: OS Independent
License-File: LICENSE
Requires-Dist: pyyaml
